{
	"animations": [
		{
			"offsets": [
				0,
				0
			],
			"loop": true,
			"fps": 12,
			"anim": "idle",
			"indices": [],
			"name": "Idle"
		},
		{
			"offsets": [
				-1,
				0
			],
			"loop": false,
			"fps": 12,
			"anim": "singLEFT",
			"indices": [],
			"name": "Left"
		},
		{
			"offsets": [
				-1,
				0
			],
			"loop": false,
			"fps": 12,
			"anim": "singDOWN",
			"indices": [],
			"name": "Down"
		},
		{
			"offsets": [
				0,
				0
			],
			"loop": false,
			"fps": 12,
			"anim": "singRIGHT",
			"indices": [],
			"name": "Right"
		},
		{
			"offsets": [
				1,
				0
			],
			"loop": false,
			"fps": 12,
			"anim": "singUP",
			"indices": [],
			"name": "Up"
		}
	],
	"no_antialiasing": true,
	"image": "characters/true-fatal",
	"position": [
		100,
		200
	],
	"healthicon": "true-fatal",
	"flip_x": false,
	"healthbar_colors": [
		255,
		60,
		110
	],
	"camera_position": [
		-810,
		-300
	],
	"sing_duration": 6.1,
	"scale": 4
}