<?xml version="1.0" encoding="utf-8"?>
<TextureAtlas imagePath="BFPhase3_Perspective_Flipped.png">
	<!-- Created with Adobe Animate version 21.0.3.38773 -->
	<!-- http://www.adobe.com/products/animate.html -->
	<SubTexture name="Down_Miss_Flip0000" x="0" y="0" width="524" height="494"/>
	<SubTexture name="Down_Miss_Flip0001" x="524" y="0" width="524" height="494"/>
	<SubTexture name="Down_Miss_Flip0002" x="1048" y="0" width="524" height="494"/>
	<SubTexture name="Down_Miss_Flip0003" x="1572" y="0" width="524" height="494"/>
	<SubTexture name="Down_Miss_Flip0004" x="2096" y="0" width="524" height="494"/>
	<SubTexture name="Down_Miss_Flip0005" x="2620" y="0" width="524" height="494"/>
	<SubTexture name="Down_Miss_Flip0006" x="3144" y="0" width="524" height="494"/>
	<SubTexture name="Down_Miss_Flip0007" x="3668" y="0" width="524" height="494"/>
	<SubTexture name="Down_Miss_Flip0008" x="4192" y="0" width="524" height="494"/>
	<SubTexture name="Down_Miss_Flip0009" x="4716" y="0" width="524" height="494"/>
	<SubTexture name="Down_Miss_Flip0010" x="5240" y="0" width="524" height="494"/>
	<SubTexture name="Down_Miss_Flip0011" x="5764" y="0" width="524" height="494"/>
	<SubTexture name="Down_Miss_Flip0012" x="6288" y="0" width="524" height="494"/>
	<SubTexture name="Down_Miss_Flip0013" x="6812" y="0" width="524" height="494"/>
	<SubTexture name="Down_Miss_Flip0014" x="7336" y="0" width="524" height="494"/>
	<SubTexture name="Down_Miss_Flip0015" x="0" y="494" width="524" height="494"/>
	<SubTexture name="Down_Miss_Flip0016" x="524" y="494" width="524" height="494"/>
	<SubTexture name="Down_Miss_Flip0017" x="1048" y="494" width="524" height="494"/>
	<SubTexture name="Down_Miss_Flip0018" x="1572" y="494" width="524" height="494"/>
	<SubTexture name="Down_Miss_Flip0019" x="2096" y="494" width="524" height="494"/>
	<SubTexture name="Down_Miss_Flip0020" x="2620" y="494" width="524" height="494"/>
	<SubTexture name="Down_Miss_Flip0021" x="3144" y="494" width="524" height="494"/>
	<SubTexture name="Down_Miss_Flip0022" x="3668" y="494" width="524" height="494"/>
	<SubTexture name="Down_Miss_Flip0023" x="4192" y="494" width="524" height="494"/>
	<SubTexture name="Idle_Flip0000" x="4716" y="494" width="514" height="493"/>
	<SubTexture name="Idle_Flip0001" x="5230" y="494" width="514" height="493"/>
	<SubTexture name="Idle_Flip0002" x="5744" y="494" width="514" height="493"/>
	<SubTexture name="Idle_Flip0003" x="6258" y="494" width="514" height="493"/>
	<SubTexture name="Idle_Flip0004" x="6772" y="494" width="514" height="493"/>
	<SubTexture name="Idle_Flip0005" x="7286" y="494" width="514" height="493"/>
	<SubTexture name="Idle_Flip0006" x="0" y="988" width="514" height="493"/>
	<SubTexture name="Idle_Flip0007" x="514" y="988" width="514" height="493"/>
	<SubTexture name="Idle_Flip0008" x="1028" y="988" width="514" height="493"/>
	<SubTexture name="Idle_Flip0009" x="1542" y="988" width="514" height="493"/>
	<SubTexture name="Idle_Flip0010" x="2056" y="988" width="514" height="493"/>
	<SubTexture name="Idle_Flip0011" x="2570" y="988" width="514" height="493"/>
	<SubTexture name="Idle_Flip0012" x="3084" y="988" width="514" height="493"/>
	<SubTexture name="Idle_Flip0013" x="3598" y="988" width="514" height="493"/>
	<SubTexture name="Left_Miss_Flip0000" x="4112" y="988" width="489" height="567"/>
	<SubTexture name="Left_Miss_Flip0001" x="4601" y="988" width="489" height="567"/>
	<SubTexture name="Left_Miss_Flip0002" x="5090" y="988" width="489" height="567"/>
	<SubTexture name="Left_Miss_Flip0003" x="5579" y="988" width="489" height="567"/>
	<SubTexture name="Left_Miss_Flip0004" x="6068" y="988" width="489" height="567"/>
	<SubTexture name="Left_Miss_Flip0005" x="6557" y="988" width="489" height="567"/>
	<SubTexture name="Left_Miss_Flip0006" x="7046" y="988" width="489" height="567"/>
	<SubTexture name="Left_Miss_Flip0007" x="7535" y="988" width="489" height="567"/>
	<SubTexture name="Left_Miss_Flip0008" x="0" y="1555" width="489" height="567"/>
	<SubTexture name="Left_Miss_Flip0009" x="489" y="1555" width="489" height="567"/>
	<SubTexture name="Left_Miss_Flip0010" x="978" y="1555" width="489" height="567"/>
	<SubTexture name="Left_Miss_Flip0011" x="1467" y="1555" width="489" height="567"/>
	<SubTexture name="Left_Miss_Flip0012" x="1956" y="1555" width="489" height="567"/>
	<SubTexture name="Left_Miss_Flip0013" x="2445" y="1555" width="489" height="567"/>
	<SubTexture name="Left_Miss_Flip0014" x="2934" y="1555" width="489" height="567"/>
	<SubTexture name="Left_Miss_Flip0015" x="3423" y="1555" width="489" height="567"/>
	<SubTexture name="Left_Miss_Flip0016" x="3912" y="1555" width="489" height="567"/>
	<SubTexture name="Left_Miss_Flip0017" x="4401" y="1555" width="489" height="567"/>
	<SubTexture name="Left_Miss_Flip0018" x="4890" y="1555" width="489" height="567"/>
	<SubTexture name="Left_Miss_Flip0019" x="5379" y="1555" width="489" height="567"/>
	<SubTexture name="Left_Miss_Flip0020" x="5868" y="1555" width="489" height="567"/>
	<SubTexture name="Left_Miss_Flip0021" x="6357" y="1555" width="489" height="567"/>
	<SubTexture name="Left_Miss_Flip0022" x="6846" y="1555" width="489" height="567"/>
	<SubTexture name="Left_Miss_Flip0023" x="7335" y="1555" width="489" height="567"/>
	<SubTexture name="Right_Miss_Flip0000" x="0" y="2122" width="530" height="592"/>
	<SubTexture name="Right_Miss_Flip0001" x="530" y="2122" width="530" height="592"/>
	<SubTexture name="Right_Miss_Flip0002" x="1060" y="2122" width="530" height="592"/>
	<SubTexture name="Right_Miss_Flip0003" x="1590" y="2122" width="530" height="592"/>
	<SubTexture name="Right_Miss_Flip0004" x="2120" y="2122" width="530" height="592"/>
	<SubTexture name="Right_Miss_Flip0005" x="2650" y="2122" width="530" height="592"/>
	<SubTexture name="Right_Miss_Flip0006" x="3180" y="2122" width="530" height="592"/>
	<SubTexture name="Right_Miss_Flip0007" x="3710" y="2122" width="530" height="592"/>
	<SubTexture name="Right_Miss_Flip0008" x="4240" y="2122" width="530" height="592"/>
	<SubTexture name="Right_Miss_Flip0009" x="4770" y="2122" width="530" height="592"/>
	<SubTexture name="Right_Miss_Flip0010" x="5300" y="2122" width="530" height="592"/>
	<SubTexture name="Right_Miss_Flip0011" x="5830" y="2122" width="530" height="592"/>
	<SubTexture name="Right_Miss_Flip0012" x="6360" y="2122" width="530" height="592"/>
	<SubTexture name="Right_Miss_Flip0013" x="6890" y="2122" width="530" height="592"/>
	<SubTexture name="Right_Miss_Flip0014" x="7420" y="2122" width="530" height="592"/>
	<SubTexture name="Right_Miss_Flip0015" x="0" y="2714" width="530" height="592"/>
	<SubTexture name="Right_Miss_Flip0016" x="530" y="2714" width="530" height="592"/>
	<SubTexture name="Right_Miss_Flip0017" x="1060" y="2714" width="530" height="592"/>
	<SubTexture name="Right_Miss_Flip0018" x="1590" y="2714" width="530" height="592"/>
	<SubTexture name="Right_Miss_Flip0019" x="2120" y="2714" width="530" height="592"/>
	<SubTexture name="Right_Miss_Flip0020" x="2650" y="2714" width="530" height="592"/>
	<SubTexture name="Right_Miss_Flip0021" x="3180" y="2714" width="530" height="592"/>
	<SubTexture name="Right_Miss_Flip0022" x="3710" y="2714" width="530" height="592"/>
	<SubTexture name="Right_Miss_Flip0023" x="4240" y="2714" width="530" height="592"/>
	<SubTexture name="Sing_Down_Flip0000" x="4770" y="2714" width="498" height="479"/>
	<SubTexture name="Sing_Down_Flip0001" x="5268" y="2714" width="498" height="479"/>
	<SubTexture name="Sing_Down_Flip0002" x="5766" y="2714" width="498" height="479"/>
	<SubTexture name="Sing_Down_Flip0003" x="6264" y="2714" width="498" height="479"/>
	<SubTexture name="Sing_Down_Flip0004" x="6762" y="2714" width="498" height="479"/>
	<SubTexture name="Sing_Down_Flip0005" x="7260" y="2714" width="498" height="479"/>
	<SubTexture name="Sing_Down_Flip0006" x="0" y="3306" width="498" height="479"/>
	<SubTexture name="Sing_Down_Flip0007" x="498" y="3306" width="498" height="479"/>
	<SubTexture name="Sing_Down_Flip0008" x="996" y="3306" width="498" height="479"/>
	<SubTexture name="Sing_Down_Flip0009" x="1494" y="3306" width="498" height="479"/>
	<SubTexture name="Sing_Down_Flip0010" x="1992" y="3306" width="498" height="479"/>
	<SubTexture name="Sing_Down_Flip0011" x="2490" y="3306" width="498" height="479"/>
	<SubTexture name="Sing_Down_Flip0012" x="2988" y="3306" width="498" height="479"/>
	<SubTexture name="Sing_Down_Flip0013" x="3486" y="3306" width="498" height="479"/>
	<SubTexture name="Sing_Down_Flip0014" x="3984" y="3306" width="498" height="479"/>
	<SubTexture name="Sing_Down_Flip0015" x="4482" y="3306" width="498" height="479"/>
	<SubTexture name="Sing_Down_Flip0016" x="4980" y="3306" width="498" height="479"/>
	<SubTexture name="Sing_Down_Flip0017" x="5478" y="3306" width="498" height="479"/>
	<SubTexture name="Sing_Down_Flip0018" x="5976" y="3306" width="498" height="479"/>
	<SubTexture name="Sing_Down_Flip0019" x="6474" y="3306" width="498" height="479"/>
	<SubTexture name="Sing_Down_Flip0020" x="6972" y="3306" width="498" height="479"/>
	<SubTexture name="Sing_Down_Flip0021" x="7470" y="3306" width="498" height="479"/>
	<SubTexture name="Sing_Down_Flip0022" x="0" y="3785" width="498" height="479"/>
	<SubTexture name="Sing_Down_Flip0023" x="498" y="3785" width="498" height="479"/>
	<SubTexture name="Sing_Left_Flip0000" x="996" y="3785" width="487" height="484"/>
	<SubTexture name="Sing_Left_Flip0001" x="1483" y="3785" width="487" height="484"/>
	<SubTexture name="Sing_Left_Flip0002" x="1970" y="3785" width="487" height="484"/>
	<SubTexture name="Sing_Left_Flip0003" x="2457" y="3785" width="487" height="484"/>
	<SubTexture name="Sing_Left_Flip0004" x="2944" y="3785" width="487" height="484"/>
	<SubTexture name="Sing_Left_Flip0005" x="3431" y="3785" width="487" height="484"/>
	<SubTexture name="Sing_Left_Flip0006" x="3918" y="3785" width="487" height="484"/>
	<SubTexture name="Sing_Left_Flip0007" x="4405" y="3785" width="487" height="484"/>
	<SubTexture name="Sing_Left_Flip0008" x="4892" y="3785" width="487" height="484"/>
	<SubTexture name="Sing_Left_Flip0009" x="5379" y="3785" width="487" height="484"/>
	<SubTexture name="Sing_Left_Flip0010" x="5866" y="3785" width="487" height="484"/>
	<SubTexture name="Sing_Left_Flip0011" x="6353" y="3785" width="487" height="484"/>
	<SubTexture name="Sing_Left_Flip0012" x="6840" y="3785" width="487" height="484"/>
	<SubTexture name="Sing_Left_Flip0013" x="7327" y="3785" width="487" height="484"/>
	<SubTexture name="Sing_Left_Flip0014" x="0" y="4269" width="487" height="484"/>
	<SubTexture name="Sing_Left_Flip0015" x="487" y="4269" width="487" height="484"/>
	<SubTexture name="Sing_Left_Flip0016" x="974" y="4269" width="487" height="484"/>
	<SubTexture name="Sing_Left_Flip0017" x="1461" y="4269" width="487" height="484"/>
	<SubTexture name="Sing_Left_Flip0018" x="1948" y="4269" width="487" height="484"/>
	<SubTexture name="Sing_Left_Flip0019" x="2435" y="4269" width="487" height="484"/>
	<SubTexture name="Sing_Left_Flip0020" x="2922" y="4269" width="487" height="484"/>
	<SubTexture name="Sing_Left_Flip0021" x="3409" y="4269" width="487" height="484"/>
	<SubTexture name="Sing_Left_Flip0022" x="3896" y="4269" width="487" height="484"/>
	<SubTexture name="Sing_Left_Flip0023" x="4383" y="4269" width="487" height="484"/>
	<SubTexture name="Sing_Right_Flip0000" x="4870" y="4269" width="523" height="507"/>
	<SubTexture name="Sing_Right_Flip0001" x="5393" y="4269" width="523" height="507"/>
	<SubTexture name="Sing_Right_Flip0002" x="5916" y="4269" width="523" height="507"/>
	<SubTexture name="Sing_Right_Flip0003" x="6439" y="4269" width="523" height="507"/>
	<SubTexture name="Sing_Right_Flip0004" x="6962" y="4269" width="523" height="507"/>
	<SubTexture name="Sing_Right_Flip0005" x="7485" y="4269" width="523" height="507"/>
	<SubTexture name="Sing_Right_Flip0006" x="0" y="4776" width="523" height="507"/>
	<SubTexture name="Sing_Right_Flip0007" x="523" y="4776" width="523" height="507"/>
	<SubTexture name="Sing_Right_Flip0008" x="1046" y="4776" width="523" height="507"/>
	<SubTexture name="Sing_Right_Flip0009" x="1569" y="4776" width="523" height="507"/>
	<SubTexture name="Sing_Right_Flip0010" x="2092" y="4776" width="523" height="507"/>
	<SubTexture name="Sing_Right_Flip0011" x="2615" y="4776" width="523" height="507"/>
	<SubTexture name="Sing_Right_Flip0012" x="3138" y="4776" width="523" height="507"/>
	<SubTexture name="Sing_Right_Flip0013" x="3661" y="4776" width="523" height="507"/>
	<SubTexture name="Sing_Right_Flip0014" x="4184" y="4776" width="523" height="507"/>
	<SubTexture name="Sing_Right_Flip0015" x="4707" y="4776" width="523" height="507"/>
	<SubTexture name="Sing_Right_Flip0016" x="5230" y="4776" width="523" height="507"/>
	<SubTexture name="Sing_Right_Flip0017" x="5753" y="4776" width="523" height="507"/>
	<SubTexture name="Sing_Right_Flip0018" x="6276" y="4776" width="523" height="507"/>
	<SubTexture name="Sing_Right_Flip0019" x="6799" y="4776" width="523" height="507"/>
	<SubTexture name="Sing_Right_Flip0020" x="7322" y="4776" width="523" height="507"/>
	<SubTexture name="Sing_Right_Flip0021" x="0" y="5283" width="523" height="507"/>
	<SubTexture name="Sing_Right_Flip0022" x="523" y="5283" width="523" height="507"/>
	<SubTexture name="Sing_Right_Flip0023" x="1046" y="5283" width="523" height="507"/>
	<SubTexture name="Sing_Up_Flip0000" x="1569" y="5283" width="461" height="552"/>
	<SubTexture name="Sing_Up_Flip0001" x="2030" y="5283" width="461" height="552"/>
	<SubTexture name="Sing_Up_Flip0002" x="2491" y="5283" width="461" height="552"/>
	<SubTexture name="Sing_Up_Flip0003" x="2952" y="5283" width="461" height="552"/>
	<SubTexture name="Sing_Up_Flip0004" x="3413" y="5283" width="461" height="552"/>
	<SubTexture name="Sing_Up_Flip0005" x="3874" y="5283" width="461" height="552"/>
	<SubTexture name="Sing_Up_Flip0006" x="4335" y="5283" width="461" height="552"/>
	<SubTexture name="Sing_Up_Flip0007" x="4796" y="5283" width="461" height="552"/>
	<SubTexture name="Sing_Up_Flip0008" x="5257" y="5283" width="461" height="552"/>
	<SubTexture name="Sing_Up_Flip0009" x="5718" y="5283" width="461" height="552"/>
	<SubTexture name="Sing_Up_Flip0010" x="6179" y="5283" width="461" height="552"/>
	<SubTexture name="Sing_Up_Flip0011" x="6640" y="5283" width="461" height="552"/>
	<SubTexture name="Sing_Up_Flip0012" x="7101" y="5283" width="461" height="552"/>
	<SubTexture name="Sing_Up_Flip0013" x="7562" y="5283" width="461" height="552"/>
	<SubTexture name="Sing_Up_Flip0014" x="0" y="5835" width="461" height="552"/>
	<SubTexture name="Sing_Up_Flip0015" x="461" y="5835" width="461" height="552"/>
	<SubTexture name="Sing_Up_Flip0016" x="922" y="5835" width="461" height="552"/>
	<SubTexture name="Sing_Up_Flip0017" x="1383" y="5835" width="461" height="552"/>
	<SubTexture name="Sing_Up_Flip0018" x="1844" y="5835" width="461" height="552"/>
	<SubTexture name="Up_Miss_Flip0000" x="2305" y="5835" width="455" height="642"/>
	<SubTexture name="Up_Miss_Flip0001" x="2760" y="5835" width="455" height="642"/>
	<SubTexture name="Up_Miss_Flip0002" x="3215" y="5835" width="455" height="642"/>
	<SubTexture name="Up_Miss_Flip0003" x="3670" y="5835" width="455" height="642"/>
	<SubTexture name="Up_Miss_Flip0004" x="4125" y="5835" width="455" height="642"/>
	<SubTexture name="Up_Miss_Flip0005" x="4580" y="5835" width="455" height="642"/>
	<SubTexture name="Up_Miss_Flip0006" x="5035" y="5835" width="455" height="642"/>
	<SubTexture name="Up_Miss_Flip0007" x="5490" y="5835" width="455" height="642"/>
	<SubTexture name="Up_Miss_Flip0008" x="5945" y="5835" width="455" height="642"/>
	<SubTexture name="Up_Miss_Flip0009" x="6400" y="5835" width="455" height="642"/>
	<SubTexture name="Up_Miss_Flip0010" x="6855" y="5835" width="455" height="642"/>
	<SubTexture name="Up_Miss_Flip0011" x="7310" y="5835" width="455" height="642"/>
	<SubTexture name="Up_Miss_Flip0012" x="0" y="6477" width="455" height="642"/>
	<SubTexture name="Up_Miss_Flip0013" x="455" y="6477" width="455" height="642"/>
	<SubTexture name="Up_Miss_Flip0014" x="910" y="6477" width="455" height="642"/>
	<SubTexture name="Up_Miss_Flip0015" x="1365" y="6477" width="455" height="642"/>
	<SubTexture name="Up_Miss_Flip0016" x="1820" y="6477" width="455" height="642"/>
	<SubTexture name="Up_Miss_Flip0017" x="2275" y="6477" width="455" height="642"/>
	<SubTexture name="Up_Miss_Flip0018" x="2730" y="6477" width="455" height="642"/>
	<SubTexture name="Up_Miss_Flip0019" x="3185" y="6477" width="455" height="642"/>
	<SubTexture name="Up_Miss_Flip0020" x="3640" y="6477" width="455" height="642"/>
	<SubTexture name="Up_Miss_Flip0021" x="4095" y="6477" width="455" height="642"/>
	<SubTexture name="Up_Miss_Flip0022" x="4550" y="6477" width="455" height="642"/>
	<SubTexture name="Up_Miss_Flip0023" x="5005" y="6477" width="455" height="642"/>
</TextureAtlas>
